apiaiwebhook/__init__.py
apiaiwebhook/apiai_webhook.py
apiaiwebhook-0.1.0.dev2.dist-info/DESCRIPTION.rst
apiaiwebhook-0.1.0.dev2.dist-info/LICENSE.txt
apiaiwebhook-0.1.0.dev2.dist-info/METADATA
apiaiwebhook-0.1.0.dev2.dist-info/RECORD
apiaiwebhook-0.1.0.dev2.dist-info/WHEEL
apiaiwebhook-0.1.0.dev2.dist-info/metadata.json
apiaiwebhook-0.1.0.dev2.dist-info/top_level.txt
