Metadata-Version: 1.1
Name: apiaiwebhook
Version: 0.1.0.dev2
Summary: API.AI Webhook is a fulfillment microframework for API.AI based on Flask for getting started quickly with API.AI webhooks.
Home-page: https://github.com/paoro-solutions/apiaiwebhook
Author: Paoro
Author-email: paoro.biz@outlook.com
License: GPLv3
Keywords: api.ai fullfillment webhook rest restful webservice dispatcher framework flask
Platform: UNKNOWN
Classifier: Development Status :: 3 - Alpha
Classifier: Intended Audience :: Developers
Classifier: License :: OSI Approved :: GNU General Public License v3 (GPLv3)
Classifier: Topic :: Communications :: Chat
Classifier: Topic :: Internet :: WWW/HTTP
Classifier: Topic :: Software Development :: Libraries :: Application Frameworks
Classifier: Operating System :: OS Independent
Classifier: Environment :: Web Environment
Classifier: Framework :: Flask
Classifier: Programming Language :: Python :: 2
Classifier: Programming Language :: Python :: 2.6
Classifier: Programming Language :: Python :: 2.7
Classifier: Programming Language :: Python :: 3
Classifier: Programming Language :: Python :: 3.3
Classifier: Programming Language :: Python :: 3.4
Classifier: Programming Language :: Python :: 3.5
Classifier: Programming Language :: Python :: 3.6
